charm_refresh_build_version/__init__.py
charm_refresh_build_version/_main.py
charm_refresh_build_version-0.4.0.dist-info/METADATA
charm_refresh_build_version-0.4.0.dist-info/WHEEL
charm_refresh_build_version-0.4.0.dist-info/entry_points.txt
charm_refresh_build_version-0.4.0.dist-info/RECORD
